source_salesloft/__init__.py
source_salesloft/custom_authenticators.py
source_salesloft/manifest.yaml
source_salesloft/run.py
source_salesloft/source.py
airbyte_source_salesloft-1.2.24.dist-info/METADATA
airbyte_source_salesloft-1.2.24.dist-info/WHEEL
airbyte_source_salesloft-1.2.24.dist-info/entry_points.txt
airbyte_source_salesloft-1.2.24.dist-info/RECORD
